stockeasy/__init__.py
stockeasy/stockeasy.py
stockeasy/utils.py
stockeasy-0.0.20220312214729.dist-info/LICENSE
stockeasy-0.0.20220312214729.dist-info/METADATA
stockeasy-0.0.20220312214729.dist-info/WHEEL
stockeasy-0.0.20220312214729.dist-info/top_level.txt
stockeasy-0.0.20220312214729.dist-info/RECORD
