Metadata-Version: 2.1
Name: stockeasy
Version: 0.0.20220312214729
Summary: A package for a quick and dirty portfolio analysis.
Home-page: https://github.com/AdamBlacke/stockeasy
Author: Adam Blacke
Author-email: adamblacke@gmail.com
License: UNKNOWN
Platform: UNKNOWN
Classifier: Programming Language :: Python :: 3.8
Classifier: License :: OSI Approved :: MIT License
Requires-Dist: pandas (==1.4.1)
